htscf/__init__.py
htscf/cli/__init__.py
htscf/cli/bdc.py
htscf/cli/forceAnalysis.py
htscf/cli/gui.py
htscf/cli/login.py
htscf/cli/logout.py
htscf/cli/main.py
htscf/cli/pyband.py
htscf/cli/pydos.py
htscf/cli/qdelAll.py
htscf/cli/qstat.py
htscf/cli/remote_sh.py
htscf/core/__init__.py
htscf/core/createStep.py
htscf/core/flow.py
htscf/core/flowManager.py
htscf/db/__init__.py
htscf/db/message.py
htscf/db/mongo.py
htscf/gui/RibbonBuilder.py
htscf/gui/UI_BuildRibbon.py
htscf/gui/UI_BuildRibbon.ui
htscf/gui/UI_YacifEditer.py
htscf/gui/UI_YacifEditer.ui
htscf/gui/__init__.py
htscf/gui/_ase.py
htscf/gui/buildRibbon.py
htscf/gui/defaultConfig.py
htscf/io/__init__.py
htscf/io/vaspIO.py
htscf/utils/__init__.py
htscf/utils/constants.py
htscf/utils/flowHandler.py
htscf/utils/logging.py
htscf/utils/qsub.py
htscf/utils/remote_sh.py
htscf/utils/tools.py
htscf/utils/vdwbulk.py
htscf-0.0.130.dist-info/LICENSE
htscf-0.0.130.dist-info/METADATA
htscf-0.0.130.dist-info/WHEEL
htscf-0.0.130.dist-info/entry_points.txt
htscf-0.0.130.dist-info/top_level.txt
htscf-0.0.130.dist-info/RECORD
