Metadata-Version: 2.1
Name: htscf
Version: 0.0.130
Summary: High-throughput computing flow
Home-page: https://cuddlebugs.asia
Author: Hao Zhao
Author-email: 601095001@qq.com
License: OSI Approved :: MIT License
Platform: Linux/Windows
Classifier: Programming Language :: Python :: 3
Classifier: License :: OSI Approved :: MIT License
Classifier: Operating System :: OS Independent
Requires-Python: >=3.8
License-File: LICENSE
Requires-Dist: ase >=3.22.1
Requires-Dist: fastapi >=0.79.0
Requires-Dist: htsct >=0.0.129
Requires-Dist: matplotlib >=3.7.2
Requires-Dist: numpy >=1.25.2
Requires-Dist: pydantic >=1.9.2
Requires-Dist: pymongo >=4.5.0
Requires-Dist: PyYAML >=5.3.1
Requires-Dist: Requests >=2.22.0
Requires-Dist: setuptools >=68.0.0
Requires-Dist: starlette >=0.19.1
Requires-Dist: toml >=0.10.2
Requires-Dist: uvicorn >=0.18.0
